perke/__init__.py
perke/__main__.py
perke/version.py
perke/base/__init__.py
perke/base/data_structures.py
perke/base/extractor.py
perke/base/readers.py
perke/base/types.py
perke/cli/__init__.py
perke/cli/base.py
perke/cli/clear.py
perke/cli/download.py
perke/resources/README.md
perke/unsupervised/__init__.py
perke/unsupervised/graph_based/__init__.py
perke/unsupervised/graph_based/multipartite_rank.py
perke/unsupervised/graph_based/position_rank.py
perke/unsupervised/graph_based/single_rank.py
perke/unsupervised/graph_based/text_rank.py
perke/unsupervised/graph_based/topic_rank.py
perke/utils/__init__.py
perke/utils/functions.py
perke/utils/string.py
perke-0.4.4.dist-info/LICENSE
perke-0.4.4.dist-info/METADATA
perke-0.4.4.dist-info/WHEEL
perke-0.4.4.dist-info/entry_points.txt
perke-0.4.4.dist-info/top_level.txt
perke-0.4.4.dist-info/RECORD
