Metadata-Version: 2.1
Name: perke
Version: 0.4.4
Summary: A keyphrase extractor for Persian
Home-page: https://github.com/alirezatheh/perke
Author: Alireza Hosseini
Author-email: alirezatheh@gmail.com
Project-URL: Bug Tracker, https://github.com/alirezatheh/perke/issues
Project-URL: Documentation, https://perke.readthedocs.io
Project-URL: Source Code, https://github.com/alirezatheh/perke
Keywords: nlp,natural-language-processing,information-retrieval,computational-linguistics,persian-language,persian-nlp,persian,keyphrase-extraction,keyphrase-extractor,keyphrase,keyword-extraction,keyword-extractor,keyword,machine-learning,ml,unsupervised-learning
Classifier: Topic :: Scientific/Engineering
Classifier: Topic :: Scientific/Engineering :: Artificial Intelligence
Classifier: Topic :: Scientific/Engineering :: Human Machine Interfaces
Classifier: Topic :: Scientific/Engineering :: Information Analysis
Classifier: Topic :: Text Processing
Classifier: Topic :: Text Processing :: Filters
Classifier: Topic :: Text Processing :: General
Classifier: Topic :: Text Processing :: Indexing
Classifier: Topic :: Text Processing :: Linguistic
Classifier: Development Status :: 5 - Production/Stable
Classifier: License :: OSI Approved :: MIT License
Classifier: Programming Language :: Python
Classifier: Programming Language :: Python :: 3
Classifier: Programming Language :: Python :: 3 :: Only
Classifier: Programming Language :: Python :: 3.8
Classifier: Programming Language :: Python :: 3.9
Classifier: Programming Language :: Python :: 3.10
Classifier: Programming Language :: Python :: 3.11
Classifier: Operating System :: OS Independent
Classifier: Intended Audience :: Developers
Classifier: Intended Audience :: Education
Classifier: Intended Audience :: Information Technology
Classifier: Intended Audience :: Science/Research
Classifier: Natural Language :: Persian
Requires-Python: >=3.8
License-File: LICENSE
Requires-Dist: hazm
Requires-Dist: nltk
Requires-Dist: networkx
Requires-Dist: scipy
Requires-Dist: typer (==0.5.0)
Requires-Dist: rich-click (==1.5.2)
Requires-Dist: gdown
